{
  "date": "2025-11-10",
  "base_currency": "EUR",
  "rates": {
    "AUD": 1.78,
    "CAD": 1.62,
    "CHF": 0.932,
    "CZK": 24.32,
    "DKK": 7.46,
    "GBP": 0.879,
    "HKD": 8.98,
    "HUF": 385,
    "JPY": 177.47,
    "KRW": 1685.73,
    "NOK": 11.75,
    "NZD": 2.05,
    "PLN": 4.24,
    "SEK": 11.02,
    "SGD": 1.5,
    "USD": 1.16,
    "ZAR": 20.01,
    "TRY": 48.8,
    "IDR": 19280.95,
    "MYR": 4.82,
    "PHP": 68.16,
    "THB": 37.41,
    "RON": 5.09,
    "MXN": 21.35,
    "CNY": 8.23,
    "BRL": 6.2,
    "INR": 102.38,
    "ILS": 3.76,
    "BGN": 1.96
  },
  "last_updated": "2025-11-10T05:16:10.716239"
}