{
  "date": "2026-06-16",
  "base_currency": "EUR",
  "rates": {
    "AUD": 1.64,
    "CAD": 1.62,
    "CHF": 0.921,
    "CZK": 24.14,
    "DKK": 7.46,
    "GBP": 0.864,
    "HKD": 9.09,
    "HUF": 350.41,
    "JPY": 185.77,
    "KRW": 1756.42,
    "NOK": 11.05,
    "NZD": 1.99,
    "PLN": 4.25,
    "SEK": 10.89,
    "SGD": 1.49,
    "USD": 1.16,
    "ZAR": 18.78,
    "TRY": 53.7,
    "IDR": 20537.65,
    "MYR": 4.7,
    "PHP": 70.06,
    "THB": 37.76,
    "RON": 5.24,
    "MXN": 19.96,
    "CNY": 7.85,
    "BRL": 5.86,
    "INR": 109.89,
    "ILS": 3.37,
    "BGN": 1.96
  },
  "last_updated": "2026-06-16T10:03:06.856691"
}